LICENSE
MANIFEST.in
README.rst
setup.cfg
setup.py
artellapipe/__init__.py
artellapipe/tools/__init__.py
artellapipe/tools/sequencespublisher/__init__.py
artellapipe/tools/sequencespublisher/__logging__.ini
artellapipe/tools/sequencespublisher/__version__.py
artellapipe/tools/sequencespublisher/core/__init__.py
artellapipe/tools/sequencespublisher/core/sequencespublisher.py
artellapipe/tools/sequencespublisher/resources/images/sequencespublisher_logo.png
artellapipe/tools/sequencespublisher/widgets/__init__.py
artellapipe/tools/sequencespublisher/widgets/sequencespublisher.py
artellapipe_tools_sequencespublisher.egg-info/PKG-INFO
artellapipe_tools_sequencespublisher.egg-info/SOURCES.txt
artellapipe_tools_sequencespublisher.egg-info/dependency_links.txt
artellapipe_tools_sequencespublisher.egg-info/not-zip-safe
artellapipe_tools_sequencespublisher.egg-info/requires.txt
artellapipe_tools_sequencespublisher.egg-info/top_level.txt
tests/__init__.py
tests/test_general.py